{
  "url": "https://www.jarsking.com/wp-content/uploads/2025/11/airless-bottle-sketch.webp",
  "title": "",
  "meta": {
    "description": "",
    "keywords": ""
  },
  "images": [],
  "text_content": {
    "title": "",
    "meta": {
      "description": "",
      "keywords": ""
    },
    "headings": [],
    "paragraphs": [],
    "lists": [],
    "tables": []
  },
  "styles": {
    "inline_styles": [],
    "css_links": [],
    "css_variables": {},
    "color_scheme": {
      "primary": [],
      "secondary": [],
      "accent": []
    },
    "typography": {
      "fonts": [],
      "sizes": []
    }
  },
  "timestamp": 1770950817.8987572
}